layginutils/__init__.py
layginutils/layginutils.cp310-win_amd64.pyd
layginutils/layginutils.cpython-310-x86_64-linux-gnu.so
layginutils-0.0.4.dist-info/METADATA
layginutils-0.0.4.dist-info/WHEEL
layginutils-0.0.4.dist-info/top_level.txt
layginutils-0.0.4.dist-info/RECORD
